napari_bioio_reader/__init__.py
napari_bioio_reader/_reader.py
napari_bioio_reader/_version.py
napari_bioio_reader/napari.yaml
napari_bioio_reader/_tests/__init__.py
napari_bioio_reader/_tests/test_reader.py
napari_bioio_reader-0.2.0.dist-info/licenses/LICENSE
napari_bioio_reader-0.2.0.dist-info/METADATA
napari_bioio_reader-0.2.0.dist-info/WHEEL
napari_bioio_reader-0.2.0.dist-info/entry_points.txt
napari_bioio_reader-0.2.0.dist-info/top_level.txt
napari_bioio_reader-0.2.0.dist-info/RECORD
