Metadata-Version: 2.4
Name: napari-bioio-reader
Version: 0.2.0
Summary: A simple plugin to use the Bioio reader in napari
Author: Laurent Guerard
Author-email: l.guerard42@gmail.com
License: 
Project-URL: Bug Tracker, https://github.com/lguerard/napari-bioio-reader/issues
Project-URL: Documentation, https://github.com/lguerard/napari-bioio-reader#README.md
Project-URL: Source Code, https://github.com/lguerard/napari-bioio-reader
Project-URL: User Support, https://github.com/lguerard/napari-bioio-reader/issues
Classifier: Development Status :: 2 - Pre-Alpha
Classifier: Framework :: napari
Classifier: Intended Audience :: Developers
Classifier: License :: OSI Approved :: BSD License
Classifier: Operating System :: OS Independent
Classifier: Programming Language :: Python
Classifier: Programming Language :: Python :: 3
Classifier: Programming Language :: Python :: 3 :: Only
Classifier: Programming Language :: Python :: 3.10
Classifier: Programming Language :: Python :: 3.11
Classifier: Programming Language :: Python :: 3.12
Classifier: Programming Language :: Python :: 3.13
Classifier: Topic :: Scientific/Engineering :: Image Processing
Requires-Python: >=3.10
License-File: LICENSE
Requires-Dist: numpy
Requires-Dist: bioio
Requires-Dist: bioio-bioformats
Requires-Dist: scyjava
Requires-Dist: napari[all]<0.7,>=0.6.2
Provides-Extra: testing
Requires-Dist: tox; extra == "testing"
Requires-Dist: pytest; extra == "testing"
Requires-Dist: pytest-cov; extra == "testing"
Dynamic: license-file
